tenhou_wall_reproducer.cpython-38-i386-linux-gnu.so
tenhou_wall_reproducer-1.2.0.dist-info/top_level.txt
tenhou_wall_reproducer-1.2.0.dist-info/WHEEL
tenhou_wall_reproducer-1.2.0.dist-info/LICENSE
tenhou_wall_reproducer-1.2.0.dist-info/METADATA
tenhou_wall_reproducer-1.2.0.dist-info/RECORD
