Metadata-Version: 2.1
Name: tenhou-wall-reproducer
Version: 1.2.0
Summary: Utility for reproducing the wall and dice information from the game seed in Tenhou platform.
Author: Sotetsu KOYAMADA
Author-email: koyamada-s@sys.i.kyoto-u.ac.jp
License-File: LICENSE
